field_manager_python_client/__init__.py
field_manager_python_client/api/__init__.py
field_manager_python_client/api/comments/__init__.py
field_manager_python_client/api/comments/delete_comment_projects_project_id_locations_location_id_comments_comment_id_delete.py
field_manager_python_client/api/comments/get_likes_projects_project_id_locations_location_id_comments_comment_id_likes_get.py
field_manager_python_client/api/comments/get_location_comments_projects_project_id_locations_location_id_comments_get.py
field_manager_python_client/api/comments/get_method_comments_projects_project_id_locations_location_id_methods_method_id_comments_get.py
field_manager_python_client/api/comments/like_comment_projects_project_id_locations_location_id_comments_comment_id_likes_post.py
field_manager_python_client/api/comments/modify_comment_projects_project_id_locations_location_id_comments_comment_id_text_put.py
field_manager_python_client/api/comments/submit_comment_projects_project_id_locations_location_id_comments_post.py
field_manager_python_client/api/comments/unlike_comment_projects_project_id_locations_location_id_comments_comment_id_likes_like_id_delete.py
field_manager_python_client/api/cross_sections/__init__.py
field_manager_python_client/api/cross_sections/create_cross_section_lines_projects_project_id_cross_sections_lines_format_post.py
field_manager_python_client/api/cross_sections/create_cross_section_projects_project_id_cross_sections_post.py
field_manager_python_client/api/cross_sections/delete_cross_section_projects_project_id_cross_sections_cross_section_id_delete.py
field_manager_python_client/api/cross_sections/delete_cross_sections_projects_project_id_cross_sections_delete.py
field_manager_python_client/api/cross_sections/get_cross_section_plot_projects_project_id_cross_sections_cross_section_id_format_get.py
field_manager_python_client/api/cross_sections/get_cross_section_projects_project_id_cross_sections_cross_section_id_get.py
field_manager_python_client-4.6.89.dist-info/METADATA
field_manager_python_client-4.6.89.dist-info/WHEEL
field_manager_python_client-4.6.89.dist-info/RECORD
