Metadata-Version: 2.1
Name: field-manager-python-client
Version: 4.6.89
Summary: A client library for accessing Field Manager Data API
Author: Jiyang Ye
Author-email: jiyang.ye@ngi.no
Maintainer: Jiyang Ye
Maintainer-email: jiyang.ye@ngi.no
Requires-Python: >=3.9,<4.0
Classifier: Programming Language :: Python :: 3
Classifier: Programming Language :: Python :: 3.9
Classifier: Programming Language :: Python :: 3.10
Classifier: Programming Language :: Python :: 3.11
Classifier: Programming Language :: Python :: 3.12
Requires-Dist: attrs (>=22.2.0)
Requires-Dist: httpx (>=0.23.0,<0.29.0)
Requires-Dist: python-dateutil (>=2.8.0,<3.0.0)
Requires-Dist: python-keycloak (>=5.5.0,<6.0.0)
